sqlmask/__init__.py
sqlmask/core.py
sqlmask-0.1.1.dist-info/METADATA
sqlmask-0.1.1.dist-info/WHEEL
sqlmask-0.1.1.dist-info/licenses/LICENSE
sqlmask-0.1.1.dist-info/RECORD
