Metadata-Version: 2.4
Name: sqlmask
Version: 0.1.1
Summary: Anonymize SQL statements.
Project-URL: Homepage, https://github.com/Byunk/sqlmask
Project-URL: Repository, https://github.com/Byunk/sqlmask
Project-URL: Issues, https://github.com/Byunk/sqlmask/issues
Author-email: Kyungho Byoun <kyungho.byoun@gmail.com>
License-Expression: BSD-3-Clause
License-File: LICENSE
Classifier: Development Status :: 4 - Beta
Classifier: Intended Audience :: Developers
Classifier: License :: OSI Approved :: BSD License
Classifier: Operating System :: OS Independent
Classifier: Programming Language :: Python :: 3
Classifier: Programming Language :: Python :: 3.10
Classifier: Programming Language :: Python :: 3.11
Classifier: Programming Language :: Python :: 3.12
Classifier: Programming Language :: Python :: 3.13
Classifier: Topic :: Database
Classifier: Topic :: Software Development :: Libraries :: Python Modules
Requires-Python: >=3.10
Requires-Dist: sqlparse<0.6,>=0.5
